{
  "section": "intune",
  "subsection": "summary",
  "label": "Intune Overzicht",
  "source": "assessment",
  "generated_at": "2026-03-28T11:11:36.2365910+01:00",
  "assessmentId": "20260328-101414",
  "summary": {
    "compliantDevices": 100,
    "totalDevices": 256,
    "compliancePercentage": 39.06,
    "intuneAvailable": true
  },
  "items": [
    {
      "Name": "Android",
      "Count": 129
    },
    {
      "Name": "Windows",
      "Count": 127
    }
  ],
  "meta": {
    "notes": [
      "Intune snapshot uit Phase 5."
    ],
    "permissions": [
      "DeviceManagementManagedDevices.Read.All",
      "DeviceManagementConfiguration.Read.All"
    ]
  }
}
